convex_style/__init__.py
convex_style/checker.py
convex_style-0.0.1.dist-info/LICENSE
convex_style-0.0.1.dist-info/METADATA
convex_style-0.0.1.dist-info/WHEEL
convex_style-0.0.1.dist-info/RECORD
